[
  {
    "name": "Advertising Equipment",
    "subs": [
      {
        "name": "Advertising Boards",
        "img": "//sc04.alicdn.com/kf/H002563001e854196a00d3183f67dca9dZ.jpeg_220x220.jpeg"
      },
      {
        "name": "Advertising Inflatables",
        "img": "//sc04.alicdn.com/kf/H1059492de47040c3aa866c5f8da9e8b0x.jpg_220x220.jpg"
      },
      {
        "name": "Advertising Light Boxes",
        "img": "//sc04.alicdn.com/kf/HTB1w2u9a42rK1RkSnhJq6ykdpXar.jpg_220x220.jpg"
      },
      {
        "name": "Billboards",
        "img": "//sc04.alicdn.com/kf/HTB19O6iLHvpK1RjSZFqq6AXUVXaM.jpg_220x220.jpg"
      },
      {
        "name": "Display Racks",
        "img": "//sc04.alicdn.com/kf/H6360888d8dd24055b91aa513f46fe5e1K.jpg_220x220.jpg"
      },
      {
        "name": "Electronic Signs",
        "img": "//sc04.alicdn.com/kf/H8820c6ddd81b4694ba8a1716f2cca0bbn.jpg_220x220.jpg"
      },
      {
        "name": "Other Advertising Equipment",
        "img": "//sc04.alicdn.com/kf/H2de7bdbc85a24e23bab813f61b8d3344X.jpg_220x220.jpg"
      },
      {
        "name": "Poster Materials",
        "img": "//sc04.alicdn.com/kf/Hfb4bb95275974773a0c473aa305b07536.jpg_220x220.jpg"
      },
      {
        "name": "Roll up Displays",
        "img": "//sc04.alicdn.com/kf/Hee825c12a9f44bcc931c8b417cc01fdad.png_220x220.png"
      }
    ]
  },
  {
    "name": "Commercial Laundry Equipment",
    "subs": [
      {
        "name": "Commercial Laundry Equipment",
        "img": "//sc04.alicdn.com/kf/H50bda4e604374f2884d1e6e1f61eb035b.jpg_220x220.jpg"
      }
    ]
  },
  {
    "name": "Commercial Robots",
    "subs": [
      {
        "name": "Commercial Robots",
        "img": "//sc04.alicdn.com/kf/H315c69432751496b91e99e0521b8fdabU.jpg_220x220.jpg"
      }
    ]
  },
  {
    "name": "Digital Signage",
    "subs": [
      {
        "name": "Digital Signage and Displays",
        "img": "//sc04.alicdn.com/kf/HLB1Qt_NU3HqK1RjSZFPq6AwapXaA.jpg_220x220.jpg"
      },
      {
        "name": "Fitness Mirrors",
        "img": "//sc04.alicdn.com/kf/H7de37b0c199a4bc6a1ced2813ab07ff1b.jpg_220x220.jpg"
      },
      {
        "name": "Hologram Equipment",
        "img": "//sc04.alicdn.com/kf/H71a0886fa9984c288c32e2f988ef5b035.jpg_220x220.jpg"
      },
      {
        "name": "Interactive Boards",
        "img": "//sc04.alicdn.com/kf/Hb2d5389f049d489f810ec41d306f7dbe9.jpg_220x220.jpg"
      }
    ]
  },
  {
    "name": "Financial Equipment",
    "subs": [
      {
        "name": "ATMs",
        "img": "//sc04.alicdn.com/kf/UTB87Nw_oTzIXKJkSafVq6yWgXXa4.jpg_220x220.jpg"
      },
      {
        "name": "Bill Counters",
        "img": "//sc04.alicdn.com/kf/Hb5542beeb6954f3d9087976a30a631c4L.jpg_220x220.jpg"
      },
      {
        "name": "Coin Counters & Sorters",
        "img": "//sc04.alicdn.com/kf/Hca57519c3fd2413d975303046d408d13R.jpg_220x220.jpg"
      },
      {
        "name": "Currency Binders",
        "img": "//sc04.alicdn.com/kf/H4a06dd23703e4868a89016a3033ebc77M.jpg_220x220.jpg"
      },
      {
        "name": "Currency Detectors",
        "img": "//sc04.alicdn.com/kf/H97e31a6d67084939bb2542fe1ea029d3t.jpg_220x220.jpg"
      },
      {
        "name": "Other Financial Equipment",
        "img": "//sc04.alicdn.com/kf/H5d6fab40598b432b95712cd9494be3c5m.jpg_220x220.jpg"
      },
      {
        "name": "Payment Kiosks",
        "img": "//sc04.alicdn.com/kf/H4d85f7e0d30646b8a2b2ec1c275a67ffS.jpg_220x220.jpg"
      },
      {
        "name": "POS Systems",
        "img": "//sc04.alicdn.com/kf/H82eca649d6924afeaaa655e40556625cI.jpg_220x220.jpg"
      }
    ]
  },
  {
    "name": "Funeral Supplies",
    "subs": [
      {
        "name": "Funeral Supplies",
        "img": "//sc04.alicdn.com/kf/H2d9aae2eb0e84a6ba1c762d6081e5260W.jpg_220x220.jpg"
      }
    ]
  },
  {
    "name": "Other Service Equipment",
    "subs": [
      {
        "name": "Other Service Equipment",
        "img": "//sc04.alicdn.com/kf/Hdac744c8210f4d7488e0e37502539491h.jpg_220x220.jpg"
      }
    ]
  },
  {
    "name": "Party Supplies",
    "subs": [
      {
        "name": "Party Supplies",
        "img": "//sc04.alicdn.com/kf/Aa0a89b1bdaf543c98dcc6c3516728b2bX.jpg_220x220.jpg"
      }
    ]
  },
  {
    "name": "Restaurant & Hotel Supplies",
    "subs": [
      {
        "name": "Cleaning Carts",
        "img": "//sc04.alicdn.com/kf/H6572ffc72c0c4df8b4b622cb55258ef2U.jpg_220x220.jpg"
      },
      {
        "name": "Food Trucks",
        "img": "//sc04.alicdn.com/kf/Hc3dff4469e2e47c2b13523b85b409539K.jpg_220x220.jpg"
      },
      {
        "name": "Hotel Amenities",
        "img": "//sc04.alicdn.com/kf/Ha87f05f9c3f34e2d89a6079058d3aed9X.jpg_220x220.jpg"
      },
      {
        "name": "Kitchen Machines",
        "img": "//sc04.alicdn.com/kf/H56a5040f053f4d5ba29359f876500fear.jpg_220x220.jpg"
      },
      {
        "name": "Other Hotel & Restaurant Supplies",
        "img": "//sc04.alicdn.com/kf/Ha109fd1caae540cfb4ab9a61091e8b46i.jpg_220x220.jpg"
      },
      {
        "name": "Serving Trays",
        "img": "//sc04.alicdn.com/kf/H7fc225f2778f4c53a061df1f2eeff8a2Y.jpg_220x220.jpg"
      },
      {
        "name": "Umbrella Wrapping Machine",
        "img": "//sc04.alicdn.com/kf/HTB18Bk9azvuK1Rjy0Faq6x2aVXaT.jpg_220x220.jpg"
      },
      {
        "name": "Coffee Bean Grinders",
        "img": "//sc04.alicdn.com/kf/Uc6f3bb6d892947cfbb631bbb8df639d3P.jpg_220x220.jpg"
      },
      {
        "name": "Coffee Bean Roaster",
        "img": "//sc04.alicdn.com/kf/A071f02797530459c8bf1049a68b4918bl.jpg_220x220.jpg"
      },
      {
        "name": "Coffee Making Equipment",
        "img": "//sc04.alicdn.com/kf/Uf519d8a64b944cad93aa822d339d3a7bj.jpg_220x220.jpg"
      },
      {
        "name": "Other Coffee Machines",
        "img": "//sc04.alicdn.com/kf/H1277207c48c9400687e2a4d74c7b9f13h.jpg_220x220.jpg"
      },
      {
        "name": "Commercial  Ice Cream Machine",
        "img": "//sc04.alicdn.com/kf/H2c8400573f274cce8f69d128ec9cea15c.jpg_220x220.jpg"
      },
      {
        "name": "Commercial Baking Oven",
        "img": "//sc04.alicdn.com/kf/H35733e34c9e847af8f1ec4cc005399fdv.jpg_220x220.jpg"
      },
      {
        "name": "Commercial Cake Machine",
        "img": "//sc04.alicdn.com/kf/H40c1bd97bb2b41f391143baad7f5fe56m.jpg_220x220.jpg"
      },
      {
        "name": "Commercial Dough Mixer",
        "img": "//sc04.alicdn.com/kf/H424e3d20f9d14c3e821bfe4cf161ff97T.jpg_220x220.jpg"
      },
      {
        "name": "Commercial Fryer",
        "img": "//sc04.alicdn.com/kf/Hd1365d336c164a088b5faa3ee0228b03F.jpg_220x220.jpg"
      },
      {
        "name": "Commercial Juice Extractor",
        "img": "//sc04.alicdn.com/kf/H5e78229b1a1844f09d63704afc5bb20bI.jpg_220x220.jpg"
      },
      {
        "name": "Commercial Popcorn Machine",
        "img": "//sc04.alicdn.com/kf/H421e4ef2e24249d08cc26dd3362e322bi.jpg_220x220.jpg"
      },
      {
        "name": "Drink Dispensers",
        "img": "//sc04.alicdn.com/kf/H534ef0a312e946c885ca083b0f4e6a68v.jpg_220x220.jpg"
      }
    ]
  },
  {
    "name": "Trade Show Equipment",
    "subs": [
      {
        "name": "Banner Stands",
        "img": "//sc04.alicdn.com/kf/H53a357e370154b9c8aaf299a4b4c1c3eF.jpg_220x220.jpg"
      },
      {
        "name": "Other Trade Show Equipment",
        "img": "//sc04.alicdn.com/kf/Hf8d9906a46434f84820c803ef7158073q.jpg_220x220.jpg"
      },
      {
        "name": "Panel Displays",
        "img": "//sc04.alicdn.com/kf/Ha62a574070c34bbebda35e887aac5b9ab.jpg_220x220.jpg"
      },
      {
        "name": "Tabletop Displays",
        "img": "//sc04.alicdn.com/kf/Heb5e96fd61de415cbdcd529cff4716b19.jpg_220x220.jpg"
      },
      {
        "name": "Truss Displays",
        "img": "//sc04.alicdn.com/kf/H26bb034e271f4708b2be48d3fdbe75b17.png_220x220.png"
      },
      {
        "name": "Atmosphere Equipment/Smog Maker/ Dry Ice",
        "img": "//sc04.alicdn.com/kf/H74ace077d39c4f7f96a15769bd5c22adg.jpg_220x220.jpg"
      },
      {
        "name": "Audio Sound Equipment",
        "img": "//sc04.alicdn.com/kf/U3afdae5635de42e8b62541d6bf1ac612M.jpeg_220x220.jpeg"
      },
      {
        "name": "DJ Controller/Audio Console Mixer",
        "img": "//sc04.alicdn.com/kf/H0ca8bd9ecb764a44a7e4fd203ea43d99A.jpg_220x220.jpg"
      },
      {
        "name": "Microphone and accessories",
        "img": "//sc04.alicdn.com/kf/H3e587e9616cf422d9dea87985e7eb19dL.jpg_220x220.jpg"
      },
      {
        "name": "Other Professional Audio, Video & Lighting",
        "img": "//sc04.alicdn.com/kf/H3fd6993a1374499cbab995a1aadc4015h.jpg_220x220.jpg"
      },
      {
        "name": "Sound Equipment/Amplifiers/Speaker",
        "img": "//sc04.alicdn.com/kf/H0d69c6827aa5457db10d6fd235377b69N.jpg_220x220.jpg"
      },
      {
        "name": "Stage Equipment System",
        "img": "//sc04.alicdn.com/kf/H2d36bac06a724e7d94539185bbae1bfds.jpg_220x220.jpg"
      },
      {
        "name": "Stage Lighting Equipment",
        "img": "//sc04.alicdn.com/kf/H72f69d7d93aa4d019584615b226bd91eN.jpg_220x220.jpg"
      }
    ]
  },
  {
    "name": "Vending Machines",
    "subs": [
      {
        "name": "Vending Machines",
        "img": "//sc04.alicdn.com/kf/HTB1YoIfRXXXXXbCXXXXq6xXFXXXy.jpg_220x220.jpg"
      }
    ]
  },
  {
    "name": "Warehousing & Supermarket Supplies",
    "subs": [
      {
        "name": "Checkout Counters",
        "img": "//sc04.alicdn.com/kf/H50546f014f6a404ba89c9bba6a422d8d3.jpg_220x220.jpg"
      },
      {
        "name": "Display Hooks",
        "img": "//sc04.alicdn.com/kf/H92bb95f3635a4b3499653d996d31ed44i.jpg_220x220.jpg"
      },
      {
        "name": "Labelers",
        "img": "//sc04.alicdn.com/kf/HTB1YmzWhlsmBKNjSZFFq6AT9VXaA.jpg_220x220.jpg"
      },
      {
        "name": "Lockers",
        "img": "//sc04.alicdn.com/kf/Hfaeb0c7fb95e47e3a1985cd5540b57424.jpg_220x220.jpg"
      },
      {
        "name": "Other Warehousing & Supermarket Supplies",
        "img": "//sc04.alicdn.com/kf/H8c3fa76a78b8453eb5ac881a68f58b8el.jpg_220x220.jpg"
      },
      {
        "name": "Promotion Tables",
        "img": "//sc04.alicdn.com/kf/Hd6145ab3fc7c4371af80daca3496b987T.png_220x220.png"
      },
      {
        "name": "Refrigeration Equipment",
        "img": "//sc04.alicdn.com/kf/H854724fdbce646d09bef932d31160afcS.jpg_220x220.jpg"
      },
      {
        "name": "Shopping Baskets",
        "img": "//sc04.alicdn.com/kf/H27ac3f60a24a44c1ac31b08e793f941a1.jpg_220x220.jpg"
      },
      {
        "name": "Shopping Trolleys & Carts",
        "img": "//sc04.alicdn.com/kf/Haf99f564075247d79e5d524af0389aacW.jpg_220x220.jpg"
      },
      {
        "name": "Showcases",
        "img": "//sc04.alicdn.com/kf/H0c6538b5a92b49febde214e271b964edU.jpg_220x220.jpg"
      },
      {
        "name": "Supermarket Shelves",
        "img": "//sc04.alicdn.com/kf/Hc2ddc69e805e44b99d77b1d99ef0350bj.jpg_220x220.jpg"
      }
    ]
  },
  {
    "name": "Wedding Supplies",
    "subs": [
      {
        "name": "Wedding Supplies",
        "img": "//sc04.alicdn.com/kf/H7d286e9999374a87b62dcf3cffcdefea7.jpg_220x220.jpg"
      }
    ]
  }
]