[
  {
    "name": "Action & Toy Figures",
    "subs": [
      {
        "name": "Action Figures",
        "img": "//sc04.alicdn.com/kf/Hf4838418a855484e916946da9afdfa69h.jpeg_220x220.jpeg"
      },
      {
        "name": "Animals & Dinosaurs",
        "img": "//sc04.alicdn.com/kf/Hc6be070015d74649aff63268fd567c446.jpg_220x220.jpg"
      },
      {
        "name": "Animation Derivatives",
        "img": "//sc04.alicdn.com/kf/H86b35cb9895a4e8d998cc40002116940I.jpg_220x220.jpg"
      },
      {
        "name": "Blind Boxes",
        "img": "//sc04.alicdn.com/kf/H6ba0015eed4742a095b1c3f9c71850f9c.jpg_220x220.jpg"
      },
      {
        "name": "Bobble Head Toy Figures",
        "img": "//sc04.alicdn.com/kf/H10d0f1f2c0264b878b8f6f690aae8f28H.jpg_220x220.jpg"
      },
      {
        "name": "Keychain Toys",
        "img": "//sc04.alicdn.com/kf/Hff372e7cda664aa0bf1a80e04a1039beh.jpg_220x220.jpg"
      },
      {
        "name": "Military Action Figures",
        "img": "//sc04.alicdn.com/kf/Hcb54c59f45624bedbd40d7e7119847b4c.jpg_220x220.jpg"
      },
      {
        "name": "Toy Figure Busts",
        "img": "//sc04.alicdn.com/kf/He25eb220be0748a6bd9be32284e81f97k.jpg_220x220.jpg"
      },
      {
        "name": "Toy Figure Display Cases",
        "img": "//sc04.alicdn.com/kf/Hb414b8cc25fb4d20b9effe435c4310f1z.jpg_220x220.jpg"
      },
      {
        "name": "Toy Figure Statues",
        "img": "//sc04.alicdn.com/kf/H3f314747711e42e589bb078650eb949cc.jpg_220x220.jpg"
      },
      {
        "name": "Toy Figure Weapons",
        "img": "//sc04.alicdn.com/kf/Hf24b1c27d8a2401992d243e96b10bf82z.jpg_220x220.jpg"
      }
    ]
  },
  {
    "name": "Arts, Crafts & DIY Toys",
    "subs": [
      {
        "name": "Air Freshener Toys",
        "img": "//sc04.alicdn.com/kf/H21874fad103d4d348adf0201210fcac6W.jpg_220x220.jpg"
      },
      {
        "name": "Candle Making Kits",
        "img": "//sc04.alicdn.com/kf/H179219a390d945a8ad82fdbecf616787t.jpg_220x220.jpg"
      },
      {
        "name": "Children Felt Craft Kits",
        "img": "//sc04.alicdn.com/kf/H255b83675fdb49f78929a3e90e6e19c4G.jpg_220x220.jpg"
      },
      {
        "name": "Children's Chalkboards",
        "img": "//sc04.alicdn.com/kf/He7d9161943fb4181ba7ba6934ff29d72q.jpg_220x220.jpg"
      },
      {
        "name": "Children's Mosaic Craft Kits",
        "img": "//sc04.alicdn.com/kf/He8919353c54b4ef5a82aafae1ef4a07fm.jpg_220x220.jpg"
      },
      {
        "name": "Children's Pencil Erasers",
        "img": "//sc04.alicdn.com/kf/A867830a63ea940d59bb37612b0d335141.jpg_220x220.jpg"
      },
      {
        "name": "Children's Scratchboard Art Kits",
        "img": "//sc04.alicdn.com/kf/Ha48b362b4f9a4f048515e3d23eeafe5eK.jpg_220x220.jpg"
      },
      {
        "name": "Children's Watercolor Paints",
        "img": "//sc04.alicdn.com/kf/H5d9c0920d4884de88d76e7884c60bd5d0.jpg_220x220.jpg"
      },
      {
        "name": "Creative Paste Toys",
        "img": "//sc04.alicdn.com/kf/H7c27e4fea52d4e7397592de4ce3dc0d7R.jpg_220x220.jpg"
      },
      {
        "name": "Dig Kits",
        "img": "//sc04.alicdn.com/kf/Hd1ff89c761b14587add6ce55e4cd69d1U.jpg_220x220.jpg"
      },
      {
        "name": "DIY Beads & Accessories",
        "img": "//sc04.alicdn.com/kf/H5972d55080e442aaaf820b2247bad781x.jpg_220x220.jpg"
      },
      {
        "name": "Jewelry Making Toys",
        "img": "//sc04.alicdn.com/kf/H09d56239d62044f1a311a9edfb2e4955q.jpg_220x220.jpg"
      },
      {
        "name": "Model Coloring Toys",
        "img": "//sc04.alicdn.com/kf/H9953313825ad4b1c97d857045443ad78X.jpg_220x220.jpg"
      },
      {
        "name": "Origami/Papercuts",
        "img": "//sc04.alicdn.com/kf/H5ae3eab7b95d4a77abfce91ef3db970c2.jpg_220x220.jpg"
      },
      {
        "name": "Sewing Toys",
        "img": "//sc04.alicdn.com/kf/H3de8224d56ed43fa8571b0422c54da72b.jpg_220x220.jpg"
      },
      {
        "name": "Soap Toys",
        "img": "//sc04.alicdn.com/kf/H15d96d1f07974450b6a39365b1120cf7D.jpg_220x220.jpg"
      },
      {
        "name": "Tie-Dye Toys",
        "img": "//sc04.alicdn.com/kf/Hcff567273ef74b6ea90afb25a1ca6b90z.jpg_220x220.jpg"
      },
      {
        "name": "Toy Stamps",
        "img": "//sc04.alicdn.com/kf/H097649b89fc64b6bba9cc8b09140a9acF.jpg_220x220.jpg"
      },
      {
        "name": "Toy Stickers",
        "img": "//sc04.alicdn.com/kf/Hf25097f8b674443288afdbaf8de0b4edQ.jpg_220x220.jpg"
      }
    ]
  },
  {
    "name": "Baby & Toddler Toys",
    "subs": [
      {
        "name": "Baby Mobiles",
        "img": "//sc04.alicdn.com/kf/A737642dc6b774991adbd4922492353daO.jpg_220x220.jpg"
      },
      {
        "name": "Baby Playpens",
        "img": "//sc04.alicdn.com/kf/Hac0267b774cd4d83a60b0faebbc097bbU.jpg_220x220.jpg"
      },
      {
        "name": "Baby Rattles",
        "img": "//sc04.alicdn.com/kf/H1a048cef919a479994a090397c7be545h.jpg_220x220.jpg"
      },
      {
        "name": "Baby Souvenirs",
        "img": "//sc04.alicdn.com/kf/H9bd2f505930f450690f8617ee90b586bF.jpg_220x220.jpg"
      },
      {
        "name": "Baby Teethers",
        "img": "//sc04.alicdn.com/kf/Hdbcb57fa5a904f50a95014b7b1e9c9daa.jpg_220x220.jpg"
      },
      {
        "name": "Baby Activity Gym",
        "img": "//sc04.alicdn.com/kf/H1792eca241574b7cb8a59b94039a7280O.jpg_220x220.jpg"
      },
      {
        "name": "Bath Toys",
        "img": "//sc04.alicdn.com/kf/H1b86b372be8743c793c9b5d5162e77d42.jpg_220x220.jpg"
      },
      {
        "name": "Bouncers & Jumpers ",
        "img": "//sc04.alicdn.com/kf/Ha5f345e7bbf7417d8b89a13e26ddc7dar.jpg_220x220.jpg"
      },
      {
        "name": "Car Seat & Stroller Toys",
        "img": "//sc04.alicdn.com/kf/H1f1dff52e7a34481a9793e70c25e6fe2d.jpg_220x220.jpg"
      },
      {
        "name": "Cloth Books",
        "img": "//sc04.alicdn.com/kf/H39bbb2e548b14a9198be1d1ce5218e97I.jpg_220x220.jpg"
      },
      {
        "name": "Harnesses & Leashes",
        "img": "//sc04.alicdn.com/kf/H7824f645f6bc4537b2f8b4497337576dX.jpg_220x220.jpg"
      },
      {
        "name": "Indoor Climbers & Play Structures",
        "img": "//sc04.alicdn.com/kf/H1baeb74afcf341cba4fa323b2ae1fa8de.png_220x220.png"
      },
      {
        "name": "Other Baby Toys",
        "img": "//sc04.alicdn.com/kf/Hfb71941b42b24435bd6f700081d45a78t.jpg_220x220.jpg"
      },
      {
        "name": "Play Mats",
        "img": "//sc04.alicdn.com/kf/H405ef4c0234e461689bad884a46f8110Z.jpg_220x220.jpg"
      },
      {
        "name": "Push/Pull Toys & Walkers",
        "img": "//sc04.alicdn.com/kf/Ha00582471eb54687ba14643b3f6a19494.jpg_220x220.jpg"
      },
      {
        "name": "Sorting, Nesting & Stacking Toys",
        "img": "//sc04.alicdn.com/kf/Hceb50cb2402448bc94dc90b488137dd5E.jpg_220x220.jpg"
      },
      {
        "name": "Swimming Pool & Accessories",
        "img": "//sc04.alicdn.com/kf/A2fe84f48d3644c52aa0487d9ff438392Y.jpg_220x220.jpg"
      }
    ]
  },
  {
    "name": "Balloons",
    "subs": [
      {
        "name": "Balloons",
        "img": "//sc04.alicdn.com/kf/Ha407f3b907244fd4baedb4d1772209f4D.jpg_220x220.jpg"
      }
    ]
  },
  {
    "name": "Blocks & Model Building Toys",
    "subs": [
      {
        "name": "Architecture/DIY House/Mininatures",
        "img": "//sc04.alicdn.com/kf/A06b66a8c983d4765a63f51261d21af6ep.jpg_220x220.jpg"
      },
      {
        "name": "Block Building Tables",
        "img": "//sc04.alicdn.com/kf/H36624bb9f71b45d8bcbc995a5b6f0d45D.jpg_220x220.jpg"
      },
      {
        "name": "Building Block Sets",
        "img": "//sc04.alicdn.com/kf/HLB1IggkU3HqK1RjSZFP763wapXaq.png_220x220.png"
      },
      {
        "name": "Dominos",
        "img": "//sc04.alicdn.com/kf/Hd5b26f47a6fd4193a55fdb059997bb1aE.jpg_220x220.jpg"
      },
      {
        "name": "Gears Sets",
        "img": "//sc04.alicdn.com/kf/H2e1d8f58573a48ba8d5d9dfbb7bd56e3M.png_220x220.png"
      },
      {
        "name": "Magnetic Blocks",
        "img": "//sc04.alicdn.com/kf/H5ab9104da4be43c7ba2e60af4f55c7c7c.jpg_220x220.jpg"
      },
      {
        "name": "Marble Runs",
        "img": "//sc04.alicdn.com/kf/H4238ba27571b48b9a424661f8f86b2d0O.jpg_220x220.jpg"
      },
      {
        "name": "Minifigures",
        "img": "//sc04.alicdn.com/kf/H25b199b211a64061b50ff33a7775e2dbv.png_220x220.png"
      },
      {
        "name": "Other Block Toys",
        "img": "//sc04.alicdn.com/kf/H42267e84662c4dd99c423077a9392a39q.jpg_220x220.jpg"
      },
      {
        "name": "Oversized Foam/Soft Plastic Blocks",
        "img": "//sc04.alicdn.com/kf/H0d4e3f8e14254fe9b3c119764644ecfcc.jpg_220x220.jpg"
      },
      {
        "name": "Screw Blocks",
        "img": "//sc04.alicdn.com/kf/Ha7dd408e3cc647cc92db0d7bad268c7cI.jpg_220x220.jpg"
      },
      {
        "name": "Stacking Toys",
        "img": "//sc04.alicdn.com/kf/Hc961f1b196e6410fad46c95ce39da04eT.jpg_220x220.jpg"
      }
    ]
  },
  {
    "name": "Classic Toys",
    "subs": [
      {
        "name": "Birds Toys",
        "img": "//sc04.alicdn.com/kf/H93542fffb37b4279bb7073b7d6fc9a418.jpg_220x220.jpg"
      },
      {
        "name": "Candy Toys",
        "img": "//sc04.alicdn.com/kf/Hce2add4a3f464b68a97e54cad1725d8cm.jpg_220x220.jpg"
      },
      {
        "name": "Fishing Toys",
        "img": "//sc04.alicdn.com/kf/Ha2ea1a94c4d54affb891a994ed7b4a45m.jpg_220x220.jpg"
      },
      {
        "name": "Glass Marbles",
        "img": "//sc04.alicdn.com/kf/H716d2e5d641644c88c720bbbf2849234P.jpg_220x220.jpg"
      },
      {
        "name": "Hamster Toys",
        "img": "https://img.alicdn.com/imgextra/i2/O1CN01lE8NXr1Y5Fe3lLByc_!!6000000003007-0-tps-400-400.jpg"
      },
      {
        "name": "Hand Clappers",
        "img": "//sc04.alicdn.com/kf/Hedc6b04b98ea45fe8fd4deb23753e336B.jpg_220x220.jpg"
      },
      {
        "name": "Hourglasses",
        "img": "//sc04.alicdn.com/kf/H27b7b7e05c9a4cd8aec2960a8c045926k.jpg_220x220.jpg"
      },
      {
        "name": "Kaleidoscopes",
        "img": "//sc04.alicdn.com/kf/Hf3eae871f7b94f2bb826c2f06d79fb5f6.jpg_220x220.jpg"
      },
      {
        "name": "Light-up Toys",
        "img": "//sc04.alicdn.com/kf/H04c5537c06d84a03a8e34a42f2b1081fc.jpg_220x220.jpg"
      },
      {
        "name": "Magic Tricks",
        "img": "//sc04.alicdn.com/kf/Hd3d7ccb4f3324cc688eb1c5bc578f65fC.jpg_220x220.jpg"
      },
      {
        "name": "Money Box",
        "img": "//sc04.alicdn.com/kf/HTB1Z69oayrxK1RkHFCcq6AQCVXaD.jpg_220x220.jpg"
      },
      {
        "name": "Noise Makers",
        "img": "//sc04.alicdn.com/kf/H6a2104f7d9344ae68e81f26730a0be19p.jpg_220x220.jpg"
      },
      {
        "name": "Other Classic Toys",
        "img": "//sc04.alicdn.com/kf/He65e062a0e09439f8b0dbb7faf08b7afy.jpg_220x220.jpg"
      },
      {
        "name": "Spinning Tops",
        "img": "//sc04.alicdn.com/kf/H7c276686e890423998d6e80b7ab3d014a.jpg_220x220.jpg"
      },
      {
        "name": "Toy Music Box",
        "img": "//sc04.alicdn.com/kf/Hc4991d01f69b42168e6f90afbd5097dfv.png_220x220.png"
      },
      {
        "name": "Wind-up Toys",
        "img": "//sc04.alicdn.com/kf/Hdc18f4ac212d4203bf3d1fa67b368b50s.jpg_220x220.jpg"
      },
      {
        "name": "Windmills",
        "img": "//sc04.alicdn.com/kf/H1d7785c160ba48f5876ffbb527ea0dcf0.jpg_220x220.jpg"
      },
      {
        "name": "Yoyos",
        "img": "//sc04.alicdn.com/kf/Hea9d7d2ef64046fbac0623cec5798f64P.jpg_220x220.jpg"
      }
    ]
  },
  {
    "name": "Dolls & Accessories",
    "subs": [
      {
        "name": "Doll Accessories",
        "img": "//sc04.alicdn.com/kf/Hb5765e8722ab4490852d34c2154e8c7cR.jpg_220x220.jpg"
      },
      {
        "name": "Doll House Accessories",
        "img": "//sc04.alicdn.com/kf/Hf2f366b7686741da9846488bb780931fo.jpg_220x220.jpg"
      },
      {
        "name": "Doll Houses",
        "img": "//sc04.alicdn.com/kf/H746bfa8878bc4ba88c3867201dfc9d88r.jpg_220x220.jpg"
      },
      {
        "name": "Dolls",
        "img": "//sc04.alicdn.com/kf/H599530f0dd90423d8ba2b0627b86c937Q.jpg_220x220.jpg"
      },
      {
        "name": "Other Dolls & Accessories",
        "img": "//sc04.alicdn.com/kf/H7a2670ba22f1427ea273ed2994bf7e11b.jpg_220x220.jpg"
      },
      {
        "name": "Reborn Dolls",
        "img": "//sc04.alicdn.com/kf/Hb6d3704c80a744d9b5a87d7e6a453b92X.jpg_220x220.jpg"
      }
    ]
  },
  {
    "name": "Dress Up & Pretend Play",
    "subs": [
      {
        "name": "Beauty & Fashion Toys",
        "img": "//sc04.alicdn.com/kf/H0517076e64f54f2c83560e9806a48b119.png_220x220.png"
      },
      {
        "name": "Cosplay Costumes",
        "img": "//sc04.alicdn.com/kf/H73f215a603d44463943b17dadecf70cd5.jpg_220x220.jpg"
      },
      {
        "name": "Doctor Toys",
        "img": "//sc04.alicdn.com/kf/H2d468f1c7e1a4af0aa751da98124ff2fr.jpg_220x220.jpg"
      },
      {
        "name": "Furniture Toys",
        "img": "//sc04.alicdn.com/kf/H232d4daf1edb4084ba2aa753b6450001q.jpg_220x220.jpg"
      },
      {
        "name": "Grocery Toys",
        "img": "//sc04.alicdn.com/kf/H856d3caa32454912a4959feb5e5749a82.jpg_220x220.jpg"
      },
      {
        "name": "Home Appliances Toys",
        "img": "//sc04.alicdn.com/kf/H6e58af2d0e4f4ef79aab4be724ec3d99A.jpg_220x220.jpg"
      },
      {
        "name": "Housekeeping Toys",
        "img": "//sc04.alicdn.com/kf/Hebb5ffbe47a44cd7b150a672b4fc24e8i.jpg_220x220.jpg"
      },
      {
        "name": "Kitchen Toys",
        "img": "//sc04.alicdn.com/kf/Hbf01df2013234a1d803d2d92166b7e7cD.jpg_220x220.jpg"
      },
      {
        "name": "Money & Banking Toys",
        "img": "//sc04.alicdn.com/kf/Hbe56b254a76147bb8fc5d1ce977fa501T.jpg_220x220.jpg"
      },
      {
        "name": "Other Pretend Play & Preschool",
        "img": "//sc04.alicdn.com/kf/H012f81b65d0343e88ba4aff433bb161d2.jpg_220x220.jpg"
      },
      {
        "name": "Other Role Playing Toys",
        "img": "//sc04.alicdn.com/kf/H914b8668f5574afd9dbd55afbb41c8c1P.jpeg_220x220.jpeg"
      },
      {
        "name": "Puppets",
        "img": "//sc04.alicdn.com/kf/H1f6276bfae3c449ea8b292d54a43f548c.jpg_220x220.jpg"
      },
      {
        "name": "Tool Toys",
        "img": "//sc04.alicdn.com/kf/Hdf4f24e380b34b1f9a37d13a0d61c148R.jpg_220x220.jpg"
      }
    ]
  },
  {
    "name": "Educational Toys",
    "subs": [
      {
        "name": "Children's Teaching Clocks",
        "img": "//sc04.alicdn.com/kf/He0ff0d9cfc354a09bc9000e9f6dd313b8.jpg_220x220.jpg"
      },
      {
        "name": "Drawing Toys",
        "img": "//sc04.alicdn.com/kf/H435d0ace23054752aac22426e12df124e.jpg_220x220.jpg"
      },
      {
        "name": "Early Learning Books",
        "img": "//sc04.alicdn.com/kf/H3b4033deb23148fd9e4d05f5f8c5e0das.jpg_220x220.jpg"
      },
      {
        "name": "Flash Cards/Cognitive Cards",
        "img": "//sc04.alicdn.com/kf/H09f81b3412214f52be76c2096a82b519T.jpg_220x220.jpg"
      },
      {
        "name": "Learning Machines",
        "img": "//sc04.alicdn.com/kf/Hd3fb8ff3f17e4a9185701130223dc366o.jpg_220x220.jpg"
      },
      {
        "name": "Magnetic Stickers",
        "img": "//sc04.alicdn.com/kf/H54ea12e54ce848d29bf3f688a6dd59eb5.jpg_220x220.jpg"
      },
      {
        "name": "Math Toys",
        "img": "//sc04.alicdn.com/kf/H9a24faebaf75409e9c2390e06461d7209.jpg_220x220.jpg"
      },
      {
        "name": "Other Educational Toys",
        "img": "//sc04.alicdn.com/kf/Hc1badf83876747e78fcbcc37e4fe9ac1o.png_220x220.png"
      },
      {
        "name": "Playdough & Slime",
        "img": "//sc04.alicdn.com/kf/H173d2674ab9946afb36279ef441c81e1N.jpg_220x220.jpg"
      },
      {
        "name": "Science & Engineering Toys",
        "img": "//sc04.alicdn.com/kf/H8d0bb3a34dd844aea6aeb9c61c4ad0fbX.jpg_220x220.jpg"
      },
      {
        "name": "Sitting Posture Corrector",
        "img": "//sc04.alicdn.com/kf/H6106314eb8bd40e696559cfb84fb6ed1c.jpg_220x220.jpg"
      },
      {
        "name": "Story Machines",
        "img": "//sc04.alicdn.com/kf/Hf5036c2b8dfb4795bc021dcc43b2edb1k.jpg_220x220.jpg"
      },
      {
        "name": "Toy Microscopes",
        "img": "//sc04.alicdn.com/kf/H5f6ae1dd9e734152a7d6c21a435ca81dY.jpg_220x220.jpg"
      },
      {
        "name": "Toy Musical Instruments",
        "img": "//sc04.alicdn.com/kf/H4c9e39197f2b46bcb353071f25ebd2adO.png_220x220.png"
      }
    ]
  },
  {
    "name": "Electronic Toys",
    "subs": [
      {
        "name": "Alarm Clocks for Kids",
        "img": "https://img.alicdn.com/imgextra/i2/O1CN01lE8NXr1Y5Fe3lLByc_!!6000000003007-0-tps-400-400.jpg"
      },
      {
        "name": "App Controlled Toys",
        "img": "//sc04.alicdn.com/kf/H9fecc2596d5e42a58ca7c7b34945a1fcO.jpg_220x220.jpg"
      },
      {
        "name": "AR/VR Toys",
        "img": "//sc04.alicdn.com/kf/H443908e61851476893df2824fa3c57417.png_220x220.png"
      },
      {
        "name": "Electronic Games",
        "img": "//sc04.alicdn.com/kf/H7e7d23bce3cd453fa0e264d23f1dcce04.jpg_220x220.jpg"
      },
      {
        "name": "Electronic Pets",
        "img": "//sc04.alicdn.com/kf/H84075a6b9af24129982249b2d4801b9ch.jpg_220x220.jpg"
      },
      {
        "name": "Karaoke Machines",
        "img": "https://img.alicdn.com/imgextra/i2/O1CN01lE8NXr1Y5Fe3lLByc_!!6000000003007-0-tps-400-400.jpg"
      },
      {
        "name": "Kids' Headphones",
        "img": "https://img.alicdn.com/imgextra/i2/O1CN01lE8NXr1Y5Fe3lLByc_!!6000000003007-0-tps-400-400.jpg"
      },
      {
        "name": "Programmable Toys",
        "img": "//sc04.alicdn.com/kf/H53026b6531134f3994a9d9ca39a945c5j.jpg_220x220.jpg"
      },
      {
        "name": "Project Toys",
        "img": "//sc04.alicdn.com/kf/H250dd976b9d1419ba985da5e22e8b32bk.jpg_220x220.jpg"
      },
      {
        "name": "Tablets for Kids",
        "img": "//sc04.alicdn.com/kf/H8cd0f16efb21437c9ecc304ad16432cby.jpg_220x220.jpg"
      },
      {
        "name": "Toy Electronic Spy Gear",
        "img": "//sc04.alicdn.com/kf/H7c047cb7b4974fae876fdc74a8686befh.jpg_220x220.jpg"
      },
      {
        "name": "Toy Watches",
        "img": "//sc04.alicdn.com/kf/H80d26390057543918ca7464bc894ba56x.jpg_220x220.jpg"
      },
      {
        "name": "Toy Cameras",
        "img": "//sc04.alicdn.com/kf/Hc65d34e082b741bf993e4c9072e1d190V.jpg_220x220.jpg"
      },
      {
        "name": "Toy Walkie Talkies",
        "img": "//sc04.alicdn.com/kf/H41e43e7e01af41f7a1c7a517621711b89.jpg_220x220.jpg"
      }
    ]
  },
  {
    "name": "Hobbies & Models",
    "subs": [
      {
        "name": "Card Album Collectors",
        "img": "//sc04.alicdn.com/kf/H69e81deace1442788a02bb3bdb1ce320x.jpg_220x220.jpg"
      },
      {
        "name": "Hobby Coin Collecting Products",
        "img": "//sc04.alicdn.com/kf/Hb2c7f2fdbb864e0d80a3fc9ffb9fdb99E.jpg_220x220.jpg"
      },
      {
        "name": "Hobby Display Cases",
        "img": "//sc04.alicdn.com/kf/Hf86b284e88044e4fa04833aa9ae6190eX.jpg_220x220.jpg"
      },
      {
        "name": "Hobby Model Paints & Painting Tools",
        "img": "https://img.alicdn.com/imgextra/i2/O1CN01lE8NXr1Y5Fe3lLByc_!!6000000003007-0-tps-400-400.jpg"
      },
      {
        "name": "Hobby Modeling Adhesives",
        "img": "https://img.alicdn.com/imgextra/i2/O1CN01lE8NXr1Y5Fe3lLByc_!!6000000003007-0-tps-400-400.jpg"
      },
      {
        "name": "Hobby Pre-Built Models",
        "img": "//sc04.alicdn.com/kf/Hd78c453715bb4b4cb328f8732d7eb3e1j.jpg_220x220.jpg"
      },
      {
        "name": "Hobby Stamp Collecting Products",
        "img": "//sc04.alicdn.com/kf/Hdafb0d0265ed49c98911d4ef8ea7457a2.jpg_220x220.jpg"
      },
      {
        "name": "Model Building Tool Kits",
        "img": "//sc04.alicdn.com/kf/H551727ce68a34e4ab7963bdcb0ebcc9dX.jpg_220x220.jpg"
      }
    ]
  },
  {
    "name": "Novelty & Gag Toys",
    "subs": [
      {
        "name": "Cartoon Hats",
        "img": "//sc04.alicdn.com/kf/H9ac1852695db44d6aac8b48619e5e8f7m.jpg_220x220.jpg"
      },
      {
        "name": "Fidget Cubes",
        "img": "//sc04.alicdn.com/kf/H63415b747181419aa0d3da5722c226dan.jpg_220x220.jpg"
      },
      {
        "name": "Fidget Spinners",
        "img": "//sc04.alicdn.com/kf/H16c7d3e6a31e4a2c94f2bdfe83480557k.jpg_220x220.jpg"
      },
      {
        "name": "Finger Skateboards & Bikes",
        "img": "//sc04.alicdn.com/kf/HTB12aKjKruWBuNjSszgq6z8jVXaH.jpg_220x220.jpg"
      },
      {
        "name": "Gags & Practical Jokes",
        "img": "//sc04.alicdn.com/kf/H146bbf07633c4ed0966efaa02bf74858j.jpg_220x220.jpg"
      },
      {
        "name": "Juggling Combos",
        "img": "//sc04.alicdn.com/kf/H009bd6ef690f41f48704e30cd5abf0abn.jpg_220x220.jpg"
      },
      {
        "name": "Other Novelty & Gag Toys",
        "img": "//sc04.alicdn.com/kf/H6140b13d143942d090f7cc5727e15aa3p.jpg_220x220.jpg"
      },
      {
        "name": "Party & Funny Masks",
        "img": "//sc04.alicdn.com/kf/H3a2df2250aa24b098b5702972c94fe24x.jpg_220x220.jpg"
      },
      {
        "name": "Solar Toys",
        "img": "//sc04.alicdn.com/kf/H0fb7e3e871da499ea0a4c76e8f07e730F.jpg_220x220.jpg"
      },
      {
        "name": "Squeeze Toys",
        "img": "//sc04.alicdn.com/kf/He5a07d296df24e3a87392f6e6fa4282c9.jpg_220x220.jpg"
      },
      {
        "name": "Temporary Tattoos",
        "img": "//sc04.alicdn.com/kf/H5d09be3d84694effbf9bee56a3140b4cs.jpg_220x220.jpg"
      }
    ]
  },
  {
    "name": "Outdoor Toys & Structures",
    "subs": [
      {
        "name": "Badminton Games",
        "img": "//sc04.alicdn.com/kf/Hab864c51bcc94393bd6dd560e707ed925.jpg_220x220.jpg"
      },
      {
        "name": "Ball Pits",
        "img": "//sc04.alicdn.com/kf/H7b7da7c0945e40d3ba14c955901340fdJ.jpg_220x220.jpg"
      },
      {
        "name": "Basketball Stand Toys",
        "img": "//sc04.alicdn.com/kf/Hf0dbe7688774428aa1131996009b9a37I.jpg_220x220.jpg"
      },
      {
        "name": "Basketball Toys",
        "img": "//sc04.alicdn.com/kf/H6ede6311572f469b818a70c7a16e8ae8q.jpg_220x220.jpg"
      },
      {
        "name": "Beach & Sand Toys",
        "img": "//sc04.alicdn.com/kf/H93aa139981a64ddaa8a88be13423f3d8j.png_220x220.png"
      },
      {
        "name": "Beer Pong",
        "img": "https://img.alicdn.com/imgextra/i2/O1CN01lE8NXr1Y5Fe3lLByc_!!6000000003007-0-tps-400-400.jpg"
      },
      {
        "name": "Bocce",
        "img": "https://img.alicdn.com/imgextra/i2/O1CN01lE8NXr1Y5Fe3lLByc_!!6000000003007-0-tps-400-400.jpg"
      },
      {
        "name": "Boomerangs",
        "img": "//sc04.alicdn.com/kf/HTB1oro0KgmTBuNjy1Xbq6yMrVXag.jpg_220x220.jpg"
      },
      {
        "name": "Boxing bag/boxing gloves",
        "img": "//sc04.alicdn.com/kf/Hc4b55c0fe4e34c96b09ebd645bb87c570.jpg_220x220.jpg"
      },
      {
        "name": "Bubble Toys",
        "img": "//sc04.alicdn.com/kf/H80fe99d60fc54a0295ee0b0f15c06bf9T.jpg_220x220.jpg"
      },
      {
        "name": "Climbing Frames",
        "img": "//sc04.alicdn.com/kf/H0b57ba4e84d04a8cb8f7d055dac44af1d.jpg_220x220.jpg"
      },
      {
        "name": "Cornhole",
        "img": "//sc04.alicdn.com/kf/Hd4ed4e06514f408cb01b275159c6ad13g.jpg_220x220.jpg"
      },
      {
        "name": "Croquet",
        "img": "//sc04.alicdn.com/kf/H66f357821cb24663b6691833cb662086t.jpg_220x220.jpg"
      },
      {
        "name": "Flying Discs & Arrows",
        "img": "//sc04.alicdn.com/kf/Hefd300350b294c139cf29499adda9d7fD.png_220x220.png"
      },
      {
        "name": "Helmets & knee pads",
        "img": "//sc04.alicdn.com/kf/Hb2f53d00311c420d9086921f9707e7f54.jpg_220x220.jpg"
      },
      {
        "name": "Horseshoe Set",
        "img": "//sc04.alicdn.com/kf/Hfa181c6f36ca4fd887282a6cc5eaf6451.jpg_220x220.jpg"
      },
      {
        "name": "Hula Hoop",
        "img": "https://img.alicdn.com/imgextra/i2/O1CN01lE8NXr1Y5Fe3lLByc_!!6000000003007-0-tps-400-400.jpg"
      },
      {
        "name": "Jump Rope",
        "img": "//sc04.alicdn.com/kf/Hc213e0a8cb53492c97f292411e8258f8S.jpg_220x220.jpg"
      },
      {
        "name": "Kites",
        "img": "//sc04.alicdn.com/kf/Hc6b8ea1ff5ff478c96773cc0c2225489A.jpg_220x220.jpg"
      },
      {
        "name": "Other Outdoor Toys & Structures",
        "img": "//sc04.alicdn.com/kf/H83401912d81f48dcb0d285d960ed78dbA.jpg_220x220.jpg"
      },
      {
        "name": "Roller Skating",
        "img": "//sc04.alicdn.com/kf/H84e84c1bbf3e4e15b42cda8e3fcb0e8eU.jpg_220x220.jpg"
      },
      {
        "name": "Sensory Integration Training Equipment",
        "img": "//sc04.alicdn.com/kf/A899851bc2fce4e128fef5826f0244a1dH.jpg_220x220.jpg"
      },
      {
        "name": "Skateboards & Skates",
        "img": "https://img.alicdn.com/imgextra/i2/O1CN01lE8NXr1Y5Fe3lLByc_!!6000000003007-0-tps-400-400.jpg"
      },
      {
        "name": "Slacklines",
        "img": "https://img.alicdn.com/imgextra/i2/O1CN01lE8NXr1Y5Fe3lLByc_!!6000000003007-0-tps-400-400.jpg"
      },
      {
        "name": "Snow Scooters",
        "img": "https://img.alicdn.com/imgextra/i2/O1CN01lE8NXr1Y5Fe3lLByc_!!6000000003007-0-tps-400-400.jpg"
      },
      {
        "name": "Snow Sleds",
        "img": "//sc04.alicdn.com/kf/Hb9b974682ef64266b05183f6f8689b7dv.jpg_220x220.jpg"
      },
      {
        "name": "Snow tubes",
        "img": "//sc04.alicdn.com/kf/A8db47f6148a84693970197cb37a59bb6e.jpg_220x220.jpg"
      },
      {
        "name": "Toss Games",
        "img": "//sc04.alicdn.com/kf/H48f8ad2521cd4e60a4b240a7d0e18ccbu.jpg_220x220.jpg"
      },
      {
        "name": "Toy Balls",
        "img": "//sc04.alicdn.com/kf/HTB11MA_X6nuK1RkSmFPq6AuzFXaD.jpg_220x220.jpg"
      },
      {
        "name": "Toy Bowlings",
        "img": "//sc04.alicdn.com/kf/Hee42ae3b028246bdbee9dfad352b46f0F.jpg_220x220.jpg"
      },
      {
        "name": "Toy Golfs",
        "img": "//sc04.alicdn.com/kf/H6d6a130436184f0ca78f5020b4381d5ap.jpg_220x220.jpg"
      },
      {
        "name": "Toy Swings Sets",
        "img": "//sc04.alicdn.com/kf/H1c3ed068701d474daec2b86e3d307a295.jpg_220x220.jpg"
      },
      {
        "name": "Toy Swords",
        "img": "//sc04.alicdn.com/kf/Hd2f52f6c971c4cf5b7fab05aa728ccde4.jpg_220x220.jpg"
      },
      {
        "name": "Toy Tents",
        "img": "//sc04.alicdn.com/kf/HTB1ky3KdbYI8KJjy0Faq6zAiVXaR.jpg_220x220.jpg"
      },
      {
        "name": "Toy Tunnels",
        "img": "//sc04.alicdn.com/kf/Hcd786c37c1764b4aa4021926f2f9670cV.png_220x220.png"
      },
      {
        "name": "Toy Seesaws",
        "img": "//sc04.alicdn.com/kf/Ha7a1b752b7f54b99b641d1ffb14991d3k.jpg_220x220.jpg"
      },
      {
        "name": "Toy Slides",
        "img": "//sc04.alicdn.com/kf/H1f7da1db268340808a982f23f449ec74M.jpg_220x220.jpg"
      },
      {
        "name": "Water Balloons",
        "img": "//sc04.alicdn.com/kf/H9b9ea792dc244caa95a84dc82359a46aF.jpg_220x220.jpg"
      },
      {
        "name": "Floating Lounger Seats",
        "img": "//sc04.alicdn.com/kf/H2cd93f35ace64169aabb33f85379bd07U.jpg_220x220.jpg"
      },
      {
        "name": "Inflatable Animal Toy",
        "img": "//sc04.alicdn.com/kf/HTB19RGJSVXXXXbkXXXXq6xXFXXXs.jpg_220x220.jpg"
      },
      {
        "name": "Inflatable Bouncer",
        "img": "//sc04.alicdn.com/kf/HTB1Ucq7acfrK1Rjy1Xdq6yemFXaA.jpg_220x220.jpg"
      },
      {
        "name": "Inflatable Bubble Tents",
        "img": "//sc04.alicdn.com/kf/Hb0f3ef9f5681443b99efee8c5042d8d6d.jpg_220x220.jpg"
      },
      {
        "name": "Inflatable Cartoon Characters",
        "img": "//sc04.alicdn.com/kf/Hc70d959b5a044173a0f300e10e6ba385c.jpg_220x220.jpg"
      },
      {
        "name": "Inflatable Roller Balls",
        "img": "https://img.alicdn.com/imgextra/i2/O1CN01lE8NXr1Y5Fe3lLByc_!!6000000003007-0-tps-400-400.jpg"
      },
      {
        "name": "Inflatable Slide",
        "img": "//sc04.alicdn.com/kf/H4671f0e2edc34e4f8fad205fcca3db46g.png_220x220.png"
      },
      {
        "name": "Inflatable Toy Accessories",
        "img": "//sc04.alicdn.com/kf/HTB1VzXnLXXXXXXiXVXXq6xXFXXXb.jpg_220x220.jpg"
      }
    ]
  },
  {
    "name": "Pools & Water Fun",
    "subs": [
      {
        "name": "Baby Pools",
        "img": "//sc04.alicdn.com/kf/Hf730561a187d457497f2f7a7c15e6620J.jpg_220x220.jpg"
      },
      {
        "name": "Kiddie Pools",
        "img": "//sc04.alicdn.com/kf/H2e393cfe77184afea70ac6a6655c74afZ.jpg_220x220.jpg"
      },
      {
        "name": "Kids Sprinklers",
        "img": "//sc04.alicdn.com/kf/H87e70bfc20a941c7b2b90d0576d0e116k.jpg_220x220.jpg"
      },
      {
        "name": "Pool Accessories",
        "img": "//sc04.alicdn.com/kf/H9e0ce0a291e24ec39f2924ec95e1996ba.jpg_220x220.jpg"
      },
      {
        "name": "Pool Noodles",
        "img": "//sc04.alicdn.com/kf/H70f3bd0e39fe4d2493d20a2674a242fbU.jpg_220x220.jpg"
      },
      {
        "name": "Pool Tables ",
        "img": "https://img.alicdn.com/imgextra/i2/O1CN01lE8NXr1Y5Fe3lLByc_!!6000000003007-0-tps-400-400.jpg"
      },
      {
        "name": "Swim Safety and Floats",
        "img": "//sc04.alicdn.com/kf/H5f026b51c19e4e09a21532ec4be30cbbo.jpg_220x220.jpg"
      },
      {
        "name": "Swimming Cap",
        "img": "https://img.alicdn.com/imgextra/i2/O1CN01lE8NXr1Y5Fe3lLByc_!!6000000003007-0-tps-400-400.jpg"
      },
      {
        "name": "Swimming Goggles",
        "img": "https://img.alicdn.com/imgextra/i2/O1CN01lE8NXr1Y5Fe3lLByc_!!6000000003007-0-tps-400-400.jpg"
      },
      {
        "name": "Swimming Pool",
        "img": "//sc04.alicdn.com/kf/H6ff5382f5a7341ad860d118a69bcb36dj.jpg_220x220.jpg"
      },
      {
        "name": "Water Slides",
        "img": "//sc04.alicdn.com/kf/H9fb85524808942e0bc363bdab4aee6d2R.jpg_220x220.jpg"
      },
      {
        "name": "Water Tables",
        "img": "https://img.alicdn.com/imgextra/i2/O1CN01lE8NXr1Y5Fe3lLByc_!!6000000003007-0-tps-400-400.jpg"
      }
    ]
  },
  {
    "name": "Promotional Toys",
    "subs": [
      {
        "name": "Promotional Toys",
        "img": "//sc04.alicdn.com/kf/A3042f19d2f434661929d40e80c2cc62bs.jpeg_220x220.jpeg"
      }
    ]
  },
  {
    "name": "Puzzle & Games",
    "subs": [
      {
        "name": "3D Puzzles",
        "img": "//sc04.alicdn.com/kf/H10cfe0b7ef634caebaf4eb40ccb0b385x.jpg_220x220.jpg"
      },
      {
        "name": "Amusement machines",
        "img": "https://img.alicdn.com/imgextra/i2/O1CN01lE8NXr1Y5Fe3lLByc_!!6000000003007-0-tps-400-400.jpg"
      },
      {
        "name": "Bingo Sets",
        "img": "https://img.alicdn.com/imgextra/i2/O1CN01lE8NXr1Y5Fe3lLByc_!!6000000003007-0-tps-400-400.jpg"
      },
      {
        "name": "Board Games",
        "img": "//sc04.alicdn.com/kf/H7b7ef9ddbbc64ec09b4fb0bdb6ddb019m.jpg_220x220.jpg"
      },
      {
        "name": "Card Games",
        "img": "//sc04.alicdn.com/kf/H133ca59dfcd8476aaa92743a2c7714edQ.jpg_220x220.jpg"
      },
      {
        "name": "Card Shuffler & dealer",
        "img": "https://img.alicdn.com/imgextra/i2/O1CN01lE8NXr1Y5Fe3lLByc_!!6000000003007-0-tps-400-400.jpg"
      },
      {
        "name": "Collectible Cards",
        "img": "//sc04.alicdn.com/kf/Hf6f1dad69ef349dcb6bcb8e4caef4ff6s.jpg_220x220.jpg"
      },
      {
        "name": "Dice Games",
        "img": "https://img.alicdn.com/imgextra/i2/O1CN01lE8NXr1Y5Fe3lLByc_!!6000000003007-0-tps-400-400.jpg"
      },
      {
        "name": "Floor Games",
        "img": "//sc04.alicdn.com/kf/H3821aa4769584e92970282a26381084cO.jpg_220x220.jpg"
      },
      {
        "name": "Fortune Telling Toys",
        "img": "//sc04.alicdn.com/kf/H91ca56d118e941beab0b8174802dbcfdn.jpg_220x220.jpg"
      },
      {
        "name": "Jigsaw Puzzles",
        "img": "//sc04.alicdn.com/kf/Hec6527d275d5435fb0dcc548b9f29531n.jpg_220x220.jpg"
      },
      {
        "name": "Magic Cubes",
        "img": "//sc04.alicdn.com/kf/Hb04616aa97254dee95e451698ae7c9f6L.jpg_220x220.jpg"
      },
      {
        "name": "Majiang machine",
        "img": "https://img.alicdn.com/imgextra/i2/O1CN01lE8NXr1Y5Fe3lLByc_!!6000000003007-0-tps-400-400.jpg"
      },
      {
        "name": "Other Puzzles",
        "img": "//sc04.alicdn.com/kf/H6c9dfca5fb6f4047854dff0581ad07c8P.jpg_220x220.jpg"
      },
      {
        "name": "Pegged Puzzles",
        "img": "//sc04.alicdn.com/kf/HTB1R0iqbbr1gK0jSZR0q6zP8XXae.jpg_220x220.jpg"
      },
      {
        "name": "Table hockey",
        "img": "https://img.alicdn.com/imgextra/i2/O1CN01lE8NXr1Y5Fe3lLByc_!!6000000003007-0-tps-400-400.jpg"
      },
      {
        "name": "Table soccer",
        "img": "//sc04.alicdn.com/kf/H7a6d912e5727426e809070cde2d18dc8N.jpg_220x220.jpg"
      },
      {
        "name": "Table tennis table",
        "img": "//sc04.alicdn.com/kf/Hdd19778223554e63b3d2a3bd82960a43Z.jpg_220x220.jpg"
      },
      {
        "name": "Trading Cards",
        "img": "https://img.alicdn.com/imgextra/i2/O1CN01lE8NXr1Y5Fe3lLByc_!!6000000003007-0-tps-400-400.jpg"
      },
      {
        "name": "Travel Games",
        "img": "//sc04.alicdn.com/kf/H16f0e21a2372412b87b0a01d5a3f72ecP.jpg_220x220.jpg"
      }
    ]
  },
  {
    "name": "Remote Control Toys",
    "subs": [
      {
        "name": "RC Animals",
        "img": "//sc04.alicdn.com/kf/H25730ddedbf94c179577933c06dd73417.jpg_220x220.jpg"
      },
      {
        "name": "RC Boat & Ship",
        "img": "//sc04.alicdn.com/kf/H2bfedadba5354575a1656ee754648047z.jpg_220x220.jpg"
      },
      {
        "name": "RC Cars",
        "img": "//sc04.alicdn.com/kf/Hfa6884fb2507431e8c29f39a2f84984f5.jpg_220x220.jpg"
      },
      {
        "name": "RC Parts & Accs",
        "img": "//sc04.alicdn.com/kf/Hc40bbd72976240868f18ff571a934874u.jpg_220x220.jpg"
      },
      {
        "name": "RC Trucks",
        "img": "//sc04.alicdn.com/kf/HLB1luKFU7voK1RjSZFwq6AiCFXaX.jpg_220x220.jpg"
      },
      {
        "name": "RC Airplanes",
        "img": "//sc04.alicdn.com/kf/Hd6bf0585d0c14fd19eea86c78764592dy.jpg_220x220.jpg"
      },
      {
        "name": "RC Drones",
        "img": "//sc04.alicdn.com/kf/H63f48a6d3d1f4ef2ba682630f95e6d5ef.png_220x220.png"
      },
      {
        "name": "RC Helicopters",
        "img": "//sc04.alicdn.com/kf/H9e83a7cc514848d780cf27e5e5147f60R.png_220x220.png"
      },
      {
        "name": "RC Motorcycles",
        "img": "//sc04.alicdn.com/kf/H9038c3d604c14a9d83f94bc95a956984k.jpg_220x220.jpg"
      },
      {
        "name": "RC Tanks",
        "img": "//sc04.alicdn.com/kf/HTB1D.d6XhD1gK0jSZFKq6AJrVXag.jpg_220x220.jpg"
      },
      {
        "name": "RC Trains",
        "img": "//sc04.alicdn.com/kf/H9f3c11529c15473c8924103e91f06ba54.jpg_220x220.jpg"
      },
      {
        "name": "Toy Robots",
        "img": "//sc04.alicdn.com/kf/Ha0837ad8eecc43bab710ee30c1fa11d9O.jpg_220x220.jpg"
      }
    ]
  },
  {
    "name": "Stuffed Animals & Plush Toys",
    "subs": [
      {
        "name": "Clothing & Accessories for Plush Stuff",
        "img": "//sc04.alicdn.com/kf/H56070cb3725349a286e579337b9b4373K.jpg_220x220.jpg"
      },
      {
        "name": "Electronic Plush Toys",
        "img": "//sc04.alicdn.com/kf/H26b8684e53e44e93b25a6062f7ecb23bx.jpg_220x220.jpg"
      },
      {
        "name": "Kid's Plush Cushion & Sofa",
        "img": "//sc04.alicdn.com/kf/H4a95e652ca7d4e0ca59d175ba272fa047.jpg_220x220.jpg"
      },
      {
        "name": "Other Toy Animals",
        "img": "//sc04.alicdn.com/kf/Hdbe85dabcac0428492ecba3eed6c5cfbj.jpg_220x220.jpg"
      },
      {
        "name": "Plush Backpacks",
        "img": "//sc04.alicdn.com/kf/H4008aae3672740cbba951e6b4148d23ce.jpg_220x220.jpg"
      },
      {
        "name": "Plush Figure Toys",
        "img": "//sc04.alicdn.com/kf/Hd70276e4b06947ca908bd1afa9f34df9G.jpg_220x220.jpg"
      },
      {
        "name": "Plush Keychains Toys",
        "img": "//sc04.alicdn.com/kf/Hce5702e46ac44dfeb69741591ee6a74bE.jpg_220x220.jpg"
      },
      {
        "name": "Plush Pillows",
        "img": "//sc04.alicdn.com/kf/H6e3e2ef11db747ae9dd2af72c388494dP.jpg_220x220.jpg"
      },
      {
        "name": "Plush Plants",
        "img": "//sc04.alicdn.com/kf/Hdde169a470f9420bb6f4879637c62881h.jpg_220x220.jpg"
      },
      {
        "name": "Plush Purses",
        "img": "//sc04.alicdn.com/kf/Hea460dbcf0bd4d798612805b8764286fo.jpg_220x220.jpg"
      },
      {
        "name": "Plush Wall Mounts",
        "img": "//sc04.alicdn.com/kf/Hb30353b694ee4e5dbfa4d887d4468ae2F.jpg_220x220.jpg"
      },
      {
        "name": "Ride On Toy Animals",
        "img": "//sc04.alicdn.com/kf/HTB1mKVlfrsTMeJjSszdq6AEupXaF.jpg_220x220.jpg"
      },
      {
        "name": "Stuffed Animal Toys",
        "img": "//sc04.alicdn.com/kf/H44186ce7f0454ddbb68d30d3271e2a99x.jpg_220x220.jpg"
      }
    ]
  },
  {
    "name": "Toy Guns",
    "subs": [
      {
        "name": "Toy Guns",
        "img": "//sc04.alicdn.com/kf/Ha912c59e2303464ca8faa42d53c4cb47T.jpg_220x220.jpg"
      }
    ]
  },
  {
    "name": "Toy Vehicle",
    "subs": [
      {
        "name": "Bumper cars",
        "img": "//sc04.alicdn.com/kf/H615d6dbf5d4f48dcac802a2035c5e444Y.jpg_220x220.jpg"
      },
      {
        "name": "Diecast Toys",
        "img": "//sc04.alicdn.com/kf/HTB1SBgzjljTBKNjSZFDq6zVgVXaG.jpg_220x220.jpg"
      },
      {
        "name": "Friction Toy Vehicle",
        "img": "//sc04.alicdn.com/kf/HLB1gChiVbvpK1RjSZPiq6zmwXXaw.jpg_220x220.jpg"
      },
      {
        "name": "Hoverboards",
        "img": "https://img.alicdn.com/imgextra/i2/O1CN01lE8NXr1Y5Fe3lLByc_!!6000000003007-0-tps-400-400.jpg"
      },
      {
        "name": "Kids bikes",
        "img": "//sc04.alicdn.com/kf/Hfdd7745aacb140138b62833fdfc33a25M.jpeg_220x220.jpeg"
      },
      {
        "name": "Kids' Balance Bikes",
        "img": "//sc04.alicdn.com/kf/H65899151786348dc9ab283bd305fc131H.jpg_220x220.jpg"
      },
      {
        "name": "Kids' Pedal Cars",
        "img": "//sc04.alicdn.com/kf/H25e0767a233d4e33ade28b99f1204a54X.jpg_220x220.jpg"
      },
      {
        "name": "Kids' Swing Car",
        "img": "//sc04.alicdn.com/kf/H33b9d30ea6cb4cb1a7c565d688104283J.jpg_220x220.jpg"
      },
      {
        "name": "Kids' Tractor/Trailer",
        "img": "//sc04.alicdn.com/kf/H384ce04bfc8b423da3bedf709810f24fB.jpg_220x220.jpg"
      },
      {
        "name": "Kids' Tricycles",
        "img": "//sc04.alicdn.com/kf/H9807e1aab4c74800bc71156246cfc272y.png_220x220.png"
      },
      {
        "name": "Kids's Electric Scooters",
        "img": "//sc04.alicdn.com/kf/Hba9f5901e96546ecb021dcc61ec7fc7dn.jpg_220x220.jpg"
      },
      {
        "name": "Other Toy Vehicles",
        "img": "//sc04.alicdn.com/kf/Hfaf523b5777a4fc58945781ea70702d60.jpg_220x220.jpg"
      },
      {
        "name": "Ride-On Accessories",
        "img": "//sc04.alicdn.com/kf/H2809d92c476743b7be784efd9789a63fk.jpg_220x220.jpg"
      },
      {
        "name": "Ride-on Cars",
        "img": "//sc04.alicdn.com/kf/H3797196adbb64724ad2699a111a73216D.jpg_220x220.jpg"
      },
      {
        "name": "Slot Toys",
        "img": "//sc04.alicdn.com/kf/He424ef74c4c0449f8c61a841ac80db57j.jpg_220x220.jpg"
      }
    ]
  }
]